kivy_deps/__init__.py
kivy_deps/sdl3/__init__.py
kivy_deps_sdl3-0.0.10.data/data/share/sdl3/bin/SDL3.dll
kivy_deps_sdl3-0.0.10.data/data/share/sdl3/bin/SDL3_image.dll
kivy_deps_sdl3-0.0.10.data/data/share/sdl3/bin/SDL3_mixer.dll
kivy_deps_sdl3-0.0.10.data/data/share/sdl3/bin/SDL3_ttf.dll
kivy_deps_sdl3-0.0.10.data/data/share/sdl3/bin/gme.dll
kivy_deps_sdl3-0.0.10.data/data/share/sdl3/bin/libxmp.dll
kivy_deps_sdl3-0.0.10.data/data/share/sdl3/bin/ogg-0.dll
kivy_deps_sdl3-0.0.10.data/data/share/sdl3/bin/opus-0.dll
kivy_deps_sdl3-0.0.10.data/data/share/sdl3/bin/opusfile-0.dll
kivy_deps_sdl3-0.0.10.data/data/share/sdl3/bin/wavpackdll.dll
kivy_deps_sdl3-0.0.10.data/data/share/sdl3/bin/pkgconfig/sdl3-image.pc
kivy_deps_sdl3-0.0.10.data/data/share/sdl3/bin/pkgconfig/sdl3-mixer.pc
kivy_deps_sdl3-0.0.10.data/data/share/sdl3/bin/pkgconfig/sdl3-ttf.pc
kivy_deps_sdl3-0.0.10.data/data/share/sdl3/bin/pkgconfig/sdl3.pc
kivy_deps_sdl3-0.0.10.dist-info/METADATA
kivy_deps_sdl3-0.0.10.dist-info/WHEEL
kivy_deps_sdl3-0.0.10.dist-info/top_level.txt
kivy_deps_sdl3-0.0.10.dist-info/RECORD
